pydgea/__init__.py
pydgea/normalization.py
pydgea/pdd.py
pydgea/prework.py
pydgea/stats.py
pydgea/utils.py
pyDGEA-0.1.1.dist-info/LICENSE
pyDGEA-0.1.1.dist-info/METADATA
pyDGEA-0.1.1.dist-info/WHEEL
pyDGEA-0.1.1.dist-info/top_level.txt
pyDGEA-0.1.1.dist-info/RECORD
