Metadata-Version: 2.1
Name: pyDGEA
Version: 0.1.1
Summary: A python package that implements differential gene expression analysis.
Author: Innocent Labs
Author-email: jakec63738@gmail.com
License: MIT
Requires-Python: >=3.9.0
License-File: LICENSE
